{
  "master_hostname": "sandeep12011.mylabserver.com",
  "master_alt_names": "puppet",
  "master_ssh_username": "root",
  "master_sudo_password": "removed",
  "master_ssh_key_file": "",
  "master_ssh_key_passphrase": "removed",
  "database": "install_postgres",
  "console_username": "sandeep.reddy127@gmail.com",
  "console_password": "removed",
  "smtp_hostname": "localhost",
  "splat": [

  ],
  "captures": [
    "monolithic"
  ],
  "type": "monolithic",
  "console_database_password": "removed",
  "console_auth_db_password": "removed",
  "puppetdb_database_password": "removed",
  "database_password": "removed"
}